blobster/__init__.py
blobster/_nbdev.py
blobster/core.py
blobster-0.0.4.dist-info/LICENSE
blobster-0.0.4.dist-info/METADATA
blobster-0.0.4.dist-info/WHEEL
blobster-0.0.4.dist-info/entry_points.txt
blobster-0.0.4.dist-info/top_level.txt
blobster-0.0.4.dist-info/RECORD
