Metadata-Version: 2.1
Name: blobster
Version: 0.0.4
Summary: A convenient way to manage your Azure Data Storage with Python.
Home-page: https://github.com/tkanngiesser/blobster
Author: Tino Kanngiesser
Author-email: tinokanngiesser@gmail.com
License: Apache Software License 2.0
Keywords: Azure Blob Storage data managing
Platform: UNKNOWN
Classifier: Development Status :: 3 - Alpha
Classifier: Intended Audience :: Developers
Classifier: License :: OSI Approved :: Apache Software License
Classifier: Natural Language :: English
Classifier: Programming Language :: Python :: 3.6
Classifier: Programming Language :: Python :: 3.7
Classifier: Programming Language :: Python :: 3.8
Requires-Python: >=3.6
Requires-Dist: pandas
Requires-Dist: fastcore
Requires-Dist: azure-storage-blob (==2.1.0)
